sdypy/FRF/__init__.py
sdypy_frf-0.1.0.dist-info/METADATA
sdypy_frf-0.1.0.dist-info/WHEEL
sdypy_frf-0.1.0.dist-info/licenses/License
sdypy_frf-0.1.0.dist-info/RECORD
