Metadata-Version: 2.1
Name: sdypy-FRF
Version: 0.1.0
Summary: Frequency response function as used in structural dynamics.
Project-URL: homepage, https://github.com/sdypy/sdypy-FRF
Project-URL: documentation, https://pyfrf.readthedocs.io/en/latest/index.html
Project-URL: source, https://github.com/sdypy/sdypy-FRF
Author-email: "Janko Slavič et al." <janko.slavic@fs.uni-lj.si>
Maintainer-email: "Janko Slavič et al." <janko.slavic@fs.uni-lj.si>
License-Expression: MIT
License-File: License
Keywords: Frequency response function,MIMO,SIMO/MISO,SISO,structural dynamics
Classifier: Development Status :: 5 - Production/Stable
Classifier: Intended Audience :: Developers
Classifier: License :: OSI Approved :: MIT License
Classifier: Programming Language :: Python :: 3.10
Classifier: Topic :: Scientific/Engineering
Requires-Python: >=3.10
Requires-Dist: pyfrf>=1.0
Provides-Extra: dev
Requires-Dist: build; extra == 'dev'
Requires-Dist: pytest; extra == 'dev'
Requires-Dist: sphinx; extra == 'dev'
Requires-Dist: sphinx-copybutton>=0.5.2; extra == 'dev'
Requires-Dist: sphinx-rtd-theme; extra == 'dev'
Requires-Dist: twine; extra == 'dev'
Requires-Dist: wheel; extra == 'dev'
